LICENSE.txt
MANIFEST.in
README.rst
setup.py
pihdf/DutFactory.py
pihdf/__init__.py
pihdf/convertible.py
pihdf/mylog.py
pihdf/schedulable.py
pihdf/testable.py
pihdf.egg-info/PKG-INFO
pihdf.egg-info/SOURCES.txt
pihdf.egg-info/dependency_links.txt
pihdf.egg-info/entry_points.txt
pihdf.egg-info/not-zip-safe
pihdf.egg-info/requires.txt
pihdf.egg-info/top_level.txt
pihdf/bin/CommandChecker.py
pihdf/bin/CommandHandler.py
pihdf/bin/__init__.py
pihdf/bin/command_line.py
pihdf/bin/docopt.py
pihdf/interfaces/Bus.py
pihdf/interfaces/Common.py
pihdf/interfaces/HSD.py
pihdf/interfaces/STAvln.py
pihdf/interfaces/__init__.py
pihdf/interfaces/data_fields.py
pihdf/printers/__init__.py
pihdf/printers/beh.py
pihdf/printers/btest_class.py
pihdf/printers/comp_list.py
pihdf/printers/custom_interfaces.py
pihdf/printers/dotty.py
pihdf/printers/gtkwave.py
pihdf/printers/ip_wrapper_gen.py
pihdf/printers/json.py
pihdf/printers/mfdesign.py
pihdf/printers/rtl.py
pihdf/printers/str_builder.py
pihdf/printers/top_class.py
pihdf/printers/utest_class.py
pihdf/printers/verilog.py