Metadata-Version: 1.1
Name: pihdf
Version: 0.1.3
Summary: Hardware Design Framework based on python and MyHDL
Home-page: https://github.com/hnikolov/pihdf.git
Author: Hristo Nikolov, Nikolay Kavaldjiev
Author-email: h.n.nikolov@gmail.com, nikolay.kavaldjiev@gmail.com
License: MIT
Keywords: myhdl pihdf fpga
Platform: UNKNOWN
Classifier: Development Status :: 3 - Alpha
Classifier: License :: OSI Approved :: MIT License
Classifier: Programming Language :: Python :: 2.7
Classifier: Topic :: Scientific/Engineering :: Electronic Design Automation (EDA)
